parsbench/__init__.py
parsbench/benchmarks/__init__.py
parsbench/benchmarks/base.py
parsbench/benchmarks/benchmark_result.py
parsbench/benchmarks/custom_benchmark.py
parsbench/benchmarks/parsinlu_benchmark.py
parsbench/models/__init__.py
parsbench/models/anthropic_interface.py
parsbench/models/base.py
parsbench/models/openai_interface.py
parsbench/models/transformers_interface.py
parsbench/scores/__init__.py
parsbench/scores/base.py
parsbench/scores/common.py
parsbench/scores/machine_translation.py
parsbench/scores/summarization.py
parsbench/tasks/__init__.py
parsbench/tasks/base/__init__.py
parsbench/tasks/base/data_loader.py
parsbench/tasks/base/evaluation_result.py
parsbench/tasks/base/helpers.py
parsbench/tasks/base/prompt_template.py
parsbench/tasks/base/task.py
parsbench/tasks/base/task_category.py
parsbench/tasks/base/task_match.py
parsbench/tasks/classification/__init__.py
parsbench/tasks/classification/parsinlu_sentiment.py
parsbench/tasks/classification/prompts/en_parsinlu_sentiment.txt
parsbench/tasks/classification/prompts/en_parsinlu_sentiment_shot.txt
parsbench/tasks/classification/prompts/fa_parsinlu_sentiment.txt
parsbench/tasks/classification/prompts/fa_parsinlu_sentiment_shot.txt
parsbench/tasks/entailment/__init__.py
parsbench/tasks/entailment/conjnli.py
parsbench/tasks/entailment/farstail.py
parsbench/tasks/entailment/parsinlu.py
parsbench/tasks/entailment/prompts/en_conjnli_entailment.txt
parsbench/tasks/entailment/prompts/en_conjnli_entailment_shot.txt
parsbench/tasks/entailment/prompts/en_parsinlu_entailment.txt
parsbench/tasks/entailment/prompts/en_parsinlu_entailment_shot.txt
parsbench/tasks/entailment/prompts/fa_conjnli_entailment.txt
parsbench/tasks/entailment/prompts/fa_conjnli_entailment_shot.txt
parsbench/tasks/entailment/prompts/fa_parsinlu_entailment.txt
parsbench/tasks/entailment/prompts/fa_parsinlu_entailment_shot.txt
parsbench/tasks/machine_translation/__init__.py
parsbench/tasks/machine_translation/helpers.py
parsbench-0.1.7.dist-info/LICENSE
parsbench-0.1.7.dist-info/METADATA
parsbench-0.1.7.dist-info/WHEEL
parsbench-0.1.7.dist-info/RECORD
