Metadata-Version: 2.1
Name: parsbench
Version: 0.1.7
Summary: ParsBench provides toolkits for benchmarking LLMs based on the Persian language tasks.
Home-page: https://parsbench.github.io/ParsBench
License: Apache-2.0
Keywords: llm,benchmarking,persian
Author: Shahriar Shariati
Author-email: shahriarshm81@gmail.com
Requires-Python: >=3.10,<3.12
Classifier: License :: OSI Approved :: Apache Software License
Classifier: Natural Language :: Persian
Classifier: Operating System :: OS Independent
Classifier: Programming Language :: Python
Classifier: Programming Language :: Python :: 3
Classifier: Programming Language :: Python :: 3.10
Classifier: Programming Language :: Python :: 3.11
Classifier: Programming Language :: Python :: 3 :: Only
Classifier: Programming Language :: Python :: 3.12
Classifier: Topic :: Scientific/Engineering :: Artificial Intelligence
Classifier: Topic :: System :: Benchmark
Requires-Dist: anthropic (>=0.30.1,<0.31.0)
Requires-Dist: datasets (>=2.20.0,<3.0.0)
Requires-Dist: hazm (>=0.10.0,<0.11.0)
Requires-Dist: jsonlines (>=4.0.0,<5.0.0)
Requires-Dist: openai (>=1.35.10,<2.0.0)
Requires-Dist: rouge-score (>=0.1.2,<0.2.0)
Requires-Dist: scikit-learn (>=1.5.1,<2.0.0)
Requires-Dist: scipy (==1.10.1)
Requires-Dist: transformers (>=4.42.3,<5.0.0)
Project-URL: Documentation, https://parsbench.github.io/ParsBench
Project-URL: Repository, https://github.com/ParsBench/ParsBench
